.travis.yml
NOTICE.txt
README.rst
bootstrap.py
buildout.cfg
eke.ecas.sublime-project
setup.cfg
setup.py
travis.cfg
docs/HISTORY.txt
docs/INSTALL.txt
docs/LICENSE.txt
eke/__init__.py
eke.ecas.egg-info/PKG-INFO
eke.ecas.egg-info/SOURCES.txt
eke.ecas.egg-info/dependency_links.txt
eke.ecas.egg-info/entry_points.txt
eke.ecas.egg-info/namespace_packages.txt
eke.ecas.egg-info/not-zip-safe
eke.ecas.egg-info/requires.txt
eke.ecas.egg-info/top_level.txt
eke/ecas/README.rst
eke/ecas/__init__.py
eke/ecas/config.py
eke/ecas/configure.zcml
eke/ecas/interfaces.py
eke/ecas/overrides.zcml
eke/ecas/testing.py
eke/ecas/upgrades.py
eke/ecas/upgrades.zcml
eke/ecas/utils.py
eke/ecas/browser/__init__.py
eke/ecas/browser/configure.zcml
eke/ecas/browser/rdf.py
eke/ecas/browser/views.py
eke/ecas/browser/images/dataset-folder.gif
eke/ecas/browser/images/dataset.gif
eke/ecas/browser/templates/dataset.pt
eke/ecas/browser/templates/dataset_summary_report.pt
eke/ecas/browser/templates/datasetfolder.pt
eke/ecas/content/__init__.py
eke/ecas/content/configure.zcml
eke/ecas/content/dataset.py
eke/ecas/content/datasetfolder.py
eke/ecas/profiles/default/catalog.xml
eke/ecas/profiles/default/factorytool.xml
eke/ecas/profiles/default/metadata.xml
eke/ecas/profiles/default/rolemap.xml
eke/ecas/profiles/default/types.xml
eke/ecas/profiles/default/types/Dataset.xml
eke/ecas/profiles/default/types/Dataset_Folder.xml
eke/ecas/templates/faceted_datasets_view.pt
eke/ecas/tests/__init__.py
eke/ecas/tests/base.py
eke/ecas/tests/testDoctest.py
eke/ecas/tests/testSetup.py